<?xml version="1.0" encoding="utf-8"?>
<!DOCTYPE hibernate-mapping PUBLIC "-//Hibernate/Hibernate Mapping DTD 3.0//EN"
"http://hibernate.sourceforge.net/hibernate-mapping-3.0.dtd">
<!-- 
    Mapping file autogenerated by MyEclipse Persistence Tools
-->
<hibernate-mapping>
    <class name="com.sis.entity.FileInfo" table="fileinfo" catalog="photographer">
        <id name="fileId" type="java.lang.Integer">
            <column name="fileID" />
            <generator class="identity"></generator>
        </id>
        <many-to-one name="folder" class="com.sis.entity.Folder" fetch="select" lazy="false">
            <column name="folderID" not-null="true" />
        </many-to-one>
        <property name="fileName" type="java.lang.String">
            <column name="fileName" length="20" not-null="true" />
        </property>
        <property name="filePath" type="java.lang.String">
            <column name="filePath" length="50" not-null="true" />
        </property>
    </class>
</hibernate-mapping>
